{
  "kind": "collectionType",
  "collectionName": "proekties",
  "info": {
    "singularName": "proekty",
    "pluralName": "proekties",
    "displayName": "Проекты",
    "description": ""
  },
  "options": {
    "draftAndPublish": true
  },
  "pluginOptions": {},
  "attributes": {
    "title": {
      "type": "string"
    },
    "gallery": {
      "type": "media",
      "multiple": true,
      "required": false,
      "allowedTypes": [
        "images",
        "videos"
      ]
    },
    "square": {
      "type": "integer"
    },
    "rooms": {
      "type": "integer"
    },
    "bathroom": {
      "type": "integer"
    },
    "terrace": {
      "type": "integer"
    },
    "wardrobe": {
      "type": "integer"
    },
    "price": {
      "type": "integer"
    },
    "location": {
      "type": "string"
    },
    "layout": {
      "type": "media",
      "multiple": false,
      "required": false,
      "allowedTypes": [
        "images",
        "videos"
      ]
    },
    "preview": {
      "type": "media",
      "multiple": false,
      "required": false,
      "allowedTypes": [
        "images"
      ]
    },
    "content": {
      "type": "blocks"
    }
  }
}
